Metadata-Version: 1.0
Name: ud-gaussian-distributions
Version: 0.1
Summary: Gaussian distributions
Home-page: UNKNOWN
Author: Sai Vignesh
Author-email: something@me.com
License: UNKNOWN
Platform: UNKNOWN
